MPLn23d.cp311-win_amd64.pyd
MPLn23d-0.0.7.dist-info/LICENSE
MPLn23d-0.0.7.dist-info/METADATA
MPLn23d-0.0.7.dist-info/WHEEL
MPLn23d-0.0.7.dist-info/top_level.txt
MPLn23d-0.0.7.dist-info/RECORD
